pbaesa/__init__.py
pbaesa/allocation.py
pbaesa/lcia.py
pbaesa/utils.py
pbaesa/data/Characterization factors_for_eco3101.xlsx
pbaesa/data/__init__.py
pbaesa-0.1.1.dist-info/licenses/LICENSE
pbaesa-0.1.1.dist-info/METADATA
pbaesa-0.1.1.dist-info/WHEEL
pbaesa-0.1.1.dist-info/top_level.txt
pbaesa-0.1.1.dist-info/RECORD
