Metadata-Version: 2.4
Name: pbaesa
Version: 0.1.1
Summary: Planetary-boundary-based Absolute Environmental Sustainability Assessment
Author-email: Jan Hartmann <jan.hartmann@ltt.rwth-aachen.de>
Maintainer-email: Jan Hartmann <jan.hartmann@ltt.rwth-aachen.de>
Project-URL: source, https://github.com/RWTH-LTT/pbaesa
Project-URL: homepage, https://github.com/RWTH-LTT/pbaesa
Project-URL: tracker, https://github.com/RWTH-LTT/pbaesa/issues
Classifier: Development Status :: 4 - Beta
Classifier: Programming Language :: Python
Classifier: Programming Language :: Python :: 3
Classifier: Programming Language :: Python :: 3.10
Classifier: Programming Language :: Python :: 3.11
Classifier: Programming Language :: Python :: 3.12
Classifier: Programming Language :: Python :: 3.13
Classifier: Natural Language :: English
Classifier: Operating System :: OS Independent
Classifier: Topic :: Scientific/Engineering
Requires-Python: >=3.9
License-File: LICENSE
Requires-Dist: pandas>=1.3.0
Requires-Dist: openpyxl>=3.0.0
Requires-Dist: bw2data>=4.0.0
Requires-Dist: bw2calc>=2.0.0
Requires-Dist: pymrio
Provides-Extra: testing
Requires-Dist: pbaesa; extra == "testing"
Requires-Dist: pytest; extra == "testing"
Requires-Dist: pytest-cov; extra == "testing"
Requires-Dist: python-coveralls; extra == "testing"
Provides-Extra: dev
Requires-Dist: build; extra == "dev"
Requires-Dist: pre-commit; extra == "dev"
Requires-Dist: pylint; extra == "dev"
Requires-Dist: pytest; extra == "dev"
Requires-Dist: pytest-cov; extra == "dev"
Requires-Dist: pytest-randomly; extra == "dev"
Requires-Dist: setuptools; extra == "dev"
Dynamic: license-file
